{"root": "https://stodevx.github.io/sga-weekly-movies/movies/2018-03-30%20Pitch%20Perfect%203", "info": {"Title": "Pitch Perfect 3", "Year": "2017", "Rated": "PG-13", "Released": "22 Dec 2017", "Runtime": "93 min", "Genre": "Comedy, Music", "Director": "Trish Sie", "Writer": "Kay Cannon (screenplay by), Mike White (screenplay by), Kay Cannon (story by), Mickey Rapkin (based on the book by)", "Actors": "Anna Kendrick, Rebel Wilson, Brittany Snow, Anna Camp", "Plot": "Following their win at the world championship, the now separated Bellas reunite for one last singing competition at an overseas USO tour, but face a group who uses both instruments and voices.", "Language": "English", "Country": "USA", "Awards": "2 wins & 1 nomination.", "Ratings": [{"Source": "Internet Movie Database", "Value": "6.1/10"}, {"Source": "Rotten Tomatoes", "Value": "32%"}, {"Source": "Metacritic", "Value": "40/100"}], "imdbID": "tt4765284", "Type": "movie", "DVD": "01 Mar 2018", "BoxOffice": "$104,880,310", "Production": "Universal Pictures", "Website": "N/A", "ReleaseDate": "2017-12-22", "Genres": ["Comedy", "Music"]}, "showings": [{"time": "2018-03-30T17:00:00-05:00", "location": "Viking Theater"}, {"time": "2018-03-30T19:30:00-05:00", "location": "Viking Theater"}, {"time": "2018-03-31T17:00:00-05:00", "location": "Viking Theater"}, {"time": "2018-03-31T19:30:00-05:00", "location": "Viking Theater"}], "poster": {"sizes": [{"url": "https://stodevx.github.io/sga-weekly-movies/movies/2018-03-30%20Pitch%20Perfect%203/poster/96.jpg", "filename": "poster/96.jpg", "width": 96, "height": 142}, {"url": "https://stodevx.github.io/sga-weekly-movies/movies/2018-03-30%20Pitch%20Perfect%203/poster/192.jpg", "filename": "poster/192.jpg", "width": 192, "height": 285}, {"url": "https://stodevx.github.io/sga-weekly-movies/movies/2018-03-30%20Pitch%20Perfect%203/poster/300.jpg", "filename": "poster/300.jpg", "width": 300, "height": 445}, {"url": "https://stodevx.github.io/sga-weekly-movies/movies/2018-03-30%20Pitch%20Perfect%203/poster/512.jpg", "filename": "poster/512.jpg", "width": 512, "height": 759}, {"url": "https://stodevx.github.io/sga-weekly-movies/movies/2018-03-30%20Pitch%20Perfect%203/poster/768.jpg", "filename": "poster/768.jpg", "width": 768, "height": 1138}, {"url": "https://stodevx.github.io/sga-weekly-movies/movies/2018-03-30%20Pitch%20Perfect%203/poster/1024.jpg", "filename": "poster/1024.jpg", "width": 1012, "height": 1500}], "colors": {"dominant": [43, 29, 12], "palette": [[233, 193, 58], [25, 16, 9], [131, 93, 23], [156, 148, 66], [132, 124, 148], [172, 100, 52]]}}, "trailers": [{"name": "Pitch Perfect 3 Trailer #1 (2017) | Movieclips Trailers", "type": "Trailer", "url": "https://www.youtube.com/watch?v=qZkuyLsN3gM", "lang": "en-US", "thumbnails": [{"url": "https://stodevx.github.io/sga-weekly-movies/movies/2018-03-30%20Pitch%20Perfect%203/trailers/qZkuyLsN3gM/small.jpg", "filename": "trailers/qZkuyLsN3gM/small.jpg", "width": 120, "height": 67}, {"url": "https://stodevx.github.io/sga-weekly-movies/movies/2018-03-30%20Pitch%20Perfect%203/trailers/qZkuyLsN3gM/mq.jpg", "filename": "trailers/qZkuyLsN3gM/mq.jpg", "width": 320, "height": 180}, {"url": "https://stodevx.github.io/sga-weekly-movies/movies/2018-03-30%20Pitch%20Perfect%203/trailers/qZkuyLsN3gM/hq.jpg", "filename": "trailers/qZkuyLsN3gM/hq.jpg", "width": 480, "height": 270}, {"url": "https://stodevx.github.io/sga-weekly-movies/movies/2018-03-30%20Pitch%20Perfect%203/trailers/qZkuyLsN3gM/lq.jpg", "filename": "trailers/qZkuyLsN3gM/lq.jpg", "width": 640, "height": 360}, {"url": "https://stodevx.github.io/sga-weekly-movies/movies/2018-03-30%20Pitch%20Perfect%203/trailers/qZkuyLsN3gM/full.jpg", "filename": "trailers/qZkuyLsN3gM/full.jpg", "width": 1280, "height": 720}], "colors": {"dominant": [197, 166, 157], "palette": [[210, 186, 180], [14, 11, 27], [98, 73, 65], [132, 124, 132], [140, 84, 36], [116, 116, 132]]}}, {"name": "Picth Perfect 3  -  Trailer #1  (ซับไทย)", "type": "Trailer", "url": "https://www.youtube.com/watch?v=WcVcaSfTwc4", "lang": "en-US", "thumbnails": [{"url": "https://stodevx.github.io/sga-weekly-movies/movies/2018-03-30%20Pitch%20Perfect%203/trailers/WcVcaSfTwc4/small.jpg", "filename": "trailers/WcVcaSfTwc4/small.jpg", "width": 120, "height": 67}, {"url": "https://stodevx.github.io/sga-weekly-movies/movies/2018-03-30%20Pitch%20Perfect%203/trailers/WcVcaSfTwc4/mq.jpg", "filename": "trailers/WcVcaSfTwc4/mq.jpg", "width": 320, "height": 180}, {"url": "https://stodevx.github.io/sga-weekly-movies/movies/2018-03-30%20Pitch%20Perfect%203/trailers/WcVcaSfTwc4/hq.jpg", "filename": "trailers/WcVcaSfTwc4/hq.jpg", "width": 480, "height": 270}, {"url": "https://stodevx.github.io/sga-weekly-movies/movies/2018-03-30%20Pitch%20Perfect%203/trailers/WcVcaSfTwc4/lq.jpg", "filename": "trailers/WcVcaSfTwc4/lq.jpg", "width": 640, "height": 360}, {"url": "https://stodevx.github.io/sga-weekly-movies/movies/2018-03-30%20Pitch%20Perfect%203/trailers/WcVcaSfTwc4/full.jpg", "filename": "trailers/WcVcaSfTwc4/full.jpg", "width": 1280, "height": 720}], "colors": {"dominant": [37, 23, 28], "palette": [[44, 26, 31], [189, 191, 205], [159, 114, 96], [105, 93, 103], [128, 136, 140], [124, 148, 156]]}}]}