{
  "trailers": [
    {
      "iso_639_1": "en",
      "iso_3166_1": "US",
      "key": "F-eMt3SrfFU",
      "name": "Trailer 1",
      "site": "YouTube",
      "size": 1080,
      "type": "Trailer",
      "url": "https://www.youtube.com/watch?v=F-eMt3SrfFU"
    },
    {
      "iso_639_1": "en",
      "iso_3166_1": "US",
      "key": "T7O7BtBnsG4",
      "name": "Official Main Trailer",
      "site": "YouTube",
      "size": 1080,
      "type": "Trailer",
      "url": "https://www.youtube.com/watch?v=T7O7BtBnsG4"
    },
    {
      "iso_639_1": "en",
      "iso_3166_1": "US",
      "key": "yM9BWtppzko",
      "name": "Announcement",
      "site": "YouTube",
      "size": 1080,
      "type": "Teaser",
      "url": "https://www.youtube.com/watch?v=yM9BWtppzko"
    },
    {
      "iso_639_1": "en",
      "iso_3166_1": "US",
      "key": "PoCAmeBosvM",
      "name": "Weathering the Storm",
      "site": "YouTube",
      "size": 1080,
      "type": "Featurette",
      "url": "https://www.youtube.com/watch?v=PoCAmeBosvM"
    },
    {
      "iso_639_1": "en",
      "iso_3166_1": "US",
      "key": "kvbiVcj4l0c",
      "name": "Weapon TV Spot",
      "site": "YouTube",
      "size": 1080,
      "type": "Teaser",
      "url": "https://www.youtube.com/watch?v=kvbiVcj4l0c"
    },
    {
      "iso_639_1": "en",
      "iso_3166_1": "US",
      "key": "Ld8JoI0Q8ZY",
      "name": "Reality",
      "site": "YouTube",
      "size": 1080,
      "type": "Featurette",
      "url": "https://www.youtube.com/watch?v=Ld8JoI0Q8ZY"
    },
    {
      "iso_639_1": "en",
      "iso_3166_1": "US",
      "key": "9b57FypHS_E",
      "name": "History",
      "site": "YouTube",
      "size": 1080,
      "type": "Featurette",
      "url": "https://www.youtube.com/watch?v=9b57FypHS_E"
    }
  ]
}
