{
  "trailers": [
    {
      "iso_639_1": "en",
      "iso_3166_1": "US",
      "key": "VEdngvMGjg0",
      "name": "Official U.S. Trailer",
      "site": "YouTube",
      "size": 1080,
      "type": "Trailer",
      "url": "https://www.youtube.com/watch?v=VEdngvMGjg0"
    },
    {
      "iso_639_1": "en",
      "iso_3166_1": "US",
      "key": "LBYwAV3w4EU",
      "name": "The Miseducation Of Cameron Post | The Interview | Official Promo",
      "site": "YouTube",
      "size": 1080,
      "type": "Teaser",
      "url": "https://www.youtube.com/watch?v=LBYwAV3w4EU"
    },
    {
      "iso_639_1": "en",
      "iso_3166_1": "US",
      "key": "vnC4gWBo3LI",
      "name": "Conversations with THE MISEDUCATION OF CAMERON POST",
      "site": "YouTube",
      "size": 1080,
      "type": "Featurette",
      "url": "https://www.youtube.com/watch?v=vnC4gWBo3LI"
    }
  ]
}
