{"root": "https://stodevx.github.io/sga-weekly-movies/movies/2018-10-26%20Halloweentown", "info": {"Title": "Halloweentown", "Year": "1998", "Rated": "TV-G", "Released": "17 Oct 1998", "Runtime": "84 min", "Genre": "Adventure, Comedy, Family", "Director": "Duwayne Dunham", "Writer": "Paul Bernbaum (story), Paul Bernbaum (teleplay), Jon Cooksey (teleplay), Ali Marie Matheson (teleplay)", "Actors": "Debbie Reynolds, Kimberly J. Brown, Judith Hoag, Joey Zimmerman", "Plot": "After learning she is a witch, a girl helps save a town full of other supernatural creatures.", "Language": "English", "Country": "USA", "Awards": "2 nominations.", "Ratings": [{"Source": "Internet Movie Database", "Value": "6.9/10"}], "imdbID": "tt0173886", "Type": "movie", "DVD": "13 Sep 2005", "BoxOffice": "N/A", "Production": "Singer/White Productions", "Website": "N/A", "ReleaseDate": "1998-10-17", "Genres": ["Adventure", "Comedy", "Family"]}, "showings": [{"time": "2018-10-26T17:00:00-05:00", "location": "Viking Theater"}, {"time": "2018-10-26T19:30:00-05:00", "location": "Viking Theater"}, {"time": "2018-10-26T22:00:00-05:00", "location": "Viking Theater"}], "poster": {"sizes": [{"url": "https://stodevx.github.io/sga-weekly-movies/movies/2018-10-26%20Halloweentown/poster/96.jpg", "filename": "poster/96.jpg", "width": 96, "height": 144}, {"url": "https://stodevx.github.io/sga-weekly-movies/movies/2018-10-26%20Halloweentown/poster/192.jpg", "filename": "poster/192.jpg", "width": 192, "height": 288}, {"url": "https://stodevx.github.io/sga-weekly-movies/movies/2018-10-26%20Halloweentown/poster/300.jpg", "filename": "poster/300.jpg", "width": 300, "height": 450}, {"url": "https://stodevx.github.io/sga-weekly-movies/movies/2018-10-26%20Halloweentown/poster/512.jpg", "filename": "poster/512.jpg", "width": 512, "height": 768}, {"url": "https://stodevx.github.io/sga-weekly-movies/movies/2018-10-26%20Halloweentown/poster/768.jpg", "filename": "poster/768.jpg", "width": 768, "height": 1152}, {"url": "https://stodevx.github.io/sga-weekly-movies/movies/2018-10-26%20Halloweentown/poster/1024.jpg", "filename": "poster/1024.jpg", "width": 1024, "height": 1536}], "colors": {"dominant": [90, 72, 128], "palette": [[98, 75, 129], [218, 169, 111], [43, 29, 28], [25, 51, 104], [85, 131, 202], [156, 164, 188]]}}, "trailers": []}