{
  "trailers": [
    {
      "iso_639_1": "en",
      "iso_3166_1": "US",
      "key": "ZDPEKXx_lAI",
      "name": "Official Trailer #2",
      "site": "YouTube",
      "size": 1080,
      "type": "Trailer",
      "url": "https://www.youtube.com/watch?v=ZDPEKXx_lAI"
    },
    {
      "iso_639_1": "en",
      "iso_3166_1": "US",
      "key": "ngiK1gQKgK8",
      "name": "Official Trailer #1",
      "site": "YouTube",
      "size": 1080,
      "type": "Trailer",
      "url": "https://www.youtube.com/watch?v=ngiK1gQKgK8"
    },
    {
      "iso_639_1": "en",
      "iso_3166_1": "US",
      "key": "ASAGdtAJPnU",
      "name": "Official Trailer #3 Final",
      "site": "YouTube",
      "size": 1080,
      "type": "Trailer",
      "url": "https://www.youtube.com/watch?v=ASAGdtAJPnU"
    },
    {
      "iso_639_1": "en",
      "iso_3166_1": "US",
      "key": "Xr7ymaCKVFo",
      "name": "Precept Discussion Video - Daveed Diggs",
      "site": "YouTube",
      "size": 1080,
      "type": "Featurette",
      "url": "https://www.youtube.com/watch?v=Xr7ymaCKVFo"
    },
    {
      "iso_639_1": "en",
      "iso_3166_1": "US",
      "key": "EXlrz2Xw37M",
      "name": "Precept Discussion Video - Stephen Chbosky",
      "site": "YouTube",
      "size": 1080,
      "type": "Featurette",
      "url": "https://www.youtube.com/watch?v=EXlrz2Xw37M"
    },
    {
      "iso_639_1": "en",
      "iso_3166_1": "US",
      "key": "_V3L9fdAR2U",
      "name": "Precept Discussion Video - R.J. Palacio",
      "site": "YouTube",
      "size": 1080,
      "type": "Featurette",
      "url": "https://www.youtube.com/watch?v=_V3L9fdAR2U"
    },
    {
      "iso_639_1": "en",
      "iso_3166_1": "US",
      "key": "MstLswTU0ZA",
      "name": "Meet Dad",
      "site": "YouTube",
      "size": 1080,
      "type": "Clip",
      "url": "https://www.youtube.com/watch?v=MstLswTU0ZA"
    },
    {
      "iso_639_1": "en",
      "iso_3166_1": "US",
      "key": "GuKvnPOGI6g",
      "name": "Meet Mr. Tushman",
      "site": "YouTube",
      "size": 1080,
      "type": "Clip",
      "url": "https://www.youtube.com/watch?v=GuKvnPOGI6g"
    },
    {
      "iso_639_1": "en",
      "iso_3166_1": "US",
      "key": "UdE6ZTLcm18",
      "name": "Meet Mr. Browne",
      "site": "YouTube",
      "size": 1080,
      "type": "Clip",
      "url": "https://www.youtube.com/watch?v=UdE6ZTLcm18"
    },
    {
      "iso_639_1": "en",
      "iso_3166_1": "US",
      "key": "5FwONUrMxDc",
      "name": "Meet Via",
      "site": "YouTube",
      "size": 1080,
      "type": "Clip",
      "url": "https://www.youtube.com/watch?v=5FwONUrMxDc"
    },
    {
      "iso_639_1": "en",
      "iso_3166_1": "US",
      "key": "PKG2_qQiB-U",
      "name": "Meet Mom",
      "site": "YouTube",
      "size": 1080,
      "type": "Clip",
      "url": "https://www.youtube.com/watch?v=PKG2_qQiB-U"
    },
    {
      "iso_639_1": "en",
      "iso_3166_1": "US",
      "key": "IJRfYBQtF8E",
      "name": "Meet Auggie",
      "site": "YouTube",
      "size": 1080,
      "type": "Clip",
      "url": "https://www.youtube.com/watch?v=IJRfYBQtF8E"
    },
    {
      "iso_639_1": "en",
      "iso_3166_1": "US",
      "key": "HMAiZHnvcdc",
      "name": "Meet Jack Will",
      "site": "YouTube",
      "size": 1080,
      "type": "Clip",
      "url": "https://www.youtube.com/watch?v=HMAiZHnvcdc"
    },
    {
      "iso_639_1": "en",
      "iso_3166_1": "US",
      "key": "Ch1bTXipncA",
      "name": "Meet Summer",
      "site": "YouTube",
      "size": 1080,
      "type": "Clip",
      "url": "https://www.youtube.com/watch?v=Ch1bTXipncA"
    },
    {
      "iso_639_1": "en",
      "iso_3166_1": "US",
      "key": "Ny9Fo2ZVByU",
      "name": "Official TV Spot - Show Them",
      "site": "YouTube",
      "size": 1080,
      "type": "Clip",
      "url": "https://www.youtube.com/watch?v=Ny9Fo2ZVByU"
    },
    {
      "iso_639_1": "en",
      "iso_3166_1": "US",
      "key": "Z6OTanu6G2c",
      "name": "Official TV Spot - Family",
      "site": "YouTube",
      "size": 1080,
      "type": "Clip",
      "url": "https://www.youtube.com/watch?v=Z6OTanu6G2c"
    },
    {
      "iso_639_1": "en",
      "iso_3166_1": "US",
      "key": "Df8ymFH_smg",
      "name": "Official Clip - Precepts",
      "site": "YouTube",
      "size": 1080,
      "type": "Clip",
      "url": "https://www.youtube.com/watch?v=Df8ymFH_smg"
    },
    {
      "iso_639_1": "en",
      "iso_3166_1": "US",
      "key": "Cp95gWHVejo",
      "name": "Official Clip - First Day",
      "site": "YouTube",
      "size": 1080,
      "type": "Clip",
      "url": "https://www.youtube.com/watch?v=Cp95gWHVejo"
    }
  ]
}
